pyethiojobs/__init__.py
pyethiojobs/filters.py
pyethiojobs/pyethiojobs.py
pyethiojobs/scaffold.py
pyethiojobs/utils.py
pyethiojobs/errors/__init__.py
pyethiojobs/handler/__init__.py
pyethiojobs/handler/handlers_holder.py
pyethiojobs/methods/__init__.py
pyethiojobs/methods/category/__init__.py
pyethiojobs/methods/category/get_categories.py
pyethiojobs/methods/category/get_category.py
pyethiojobs/methods/decorators/__init__.py
pyethiojobs/methods/decorators/on_new_job.py
pyethiojobs/methods/gov/__init__.py
pyethiojobs/methods/gov/get_gov_job_details.py
pyethiojobs/methods/gov/get_gov_jobs.py
pyethiojobs/methods/job/__init__.py
pyethiojobs/methods/job/get_job.py
pyethiojobs/methods/job/get_latest_jobs.py
pyethiojobs/methods/search/__init__.py
pyethiojobs/methods/search/search.py
pyethiojobs/methods/utlis/__init__.py
pyethiojobs/methods/utlis/convert_to_pdf.py
pyethiojobs/methods/utlis/get_job_detail.py
pyethiojobs/methods/utlis/get_jobs.py
pyethiojobs/methods/utlis/run.py
pyethiojobs/types/__init__.py
pyethiojobs/types/category/__init__.py
pyethiojobs/types/category/category.py
pyethiojobs/types/employment/__init__.py
pyethiojobs/types/employment/employment_type.py
pyethiojobs/types/jobs/__init__.py
pyethiojobs/types/jobs/gov_job.py
pyethiojobs/types/jobs/gov_job_details.py
pyethiojobs/types/jobs/identifier.py
pyethiojobs/types/jobs/job.py
pyethiojobs/types/jobs/job_details.py
pyethiojobs/types/jobs/job_type.py
pyethiojobs/types/jobs/location.py
pyEthioJobs-0.0.8.dist-info/LICENSE
pyEthioJobs-0.0.8.dist-info/METADATA
pyEthioJobs-0.0.8.dist-info/WHEEL
pyEthioJobs-0.0.8.dist-info/top_level.txt
pyEthioJobs-0.0.8.dist-info/RECORD
