Metadata-Version: 2.1
Name: pyEthioJobs
Version: 0.0.8
Summary: A python package to scrape jobs from ethiojobs.net
Home-page: https://github.com/wizkiye/pyEthioJobs
Author: Kidus
Author-email: wizkiye@gmail.com
License-File: LICENSE
Requires-Dist: bs4
Requires-Dist: httpx
Requires-Dist: lxml
